prometheus_api_client/__init__.py
prometheus_api_client/exceptions.py
prometheus_api_client/metric.py
prometheus_api_client/metric_plot.py
prometheus_api_client/metric_range_df.py
prometheus_api_client/metric_snapshot_df.py
prometheus_api_client/metrics_list.py
prometheus_api_client/prometheus_connect.py
prometheus_api_client/py.typed
prometheus_api_client/utils.py
prometheus_api_client_optional_matplotlib-0.6.0.dist-info/licenses/LICENSE
tests/__init__.py
tests/mocked_network.py
tests/test_metric.py
tests/test_metric_range_df.py
tests/test_metric_snapshot_df.py
tests/test_metrics_list.py
tests/test_prometheus_connect.py
tests/test_with_metrics.py
prometheus_api_client_optional_matplotlib-0.6.0.dist-info/METADATA
prometheus_api_client_optional_matplotlib-0.6.0.dist-info/WHEEL
prometheus_api_client_optional_matplotlib-0.6.0.dist-info/top_level.txt
prometheus_api_client_optional_matplotlib-0.6.0.dist-info/RECORD
