Metadata-Version: 2.4
Name: prometheus-api-client-optional-matplotlib
Version: 0.6.0
Summary: A Python API client for Prometheus with optional matplotlib dependency
Home-page: https://github.com/4n4nd/prometheus-api-client-python
Author: Anand Sanmukhani
Author-email: asanmukhani@microsoft.com
Classifier: Programming Language :: Python :: 3.13
Classifier: License :: OSI Approved :: MIT License
Classifier: Operating System :: OS Independent
License-File: LICENSE
Requires-Dist: requests
Requires-Dist: dateparser
Requires-Dist: pandas>=1.4.0
Requires-Dist: numpy
Requires-Dist: httmock
Dynamic: author
Dynamic: author-email
Dynamic: classifier
Dynamic: description
Dynamic: description-content-type
Dynamic: home-page
Dynamic: license-file
Dynamic: requires-dist
Dynamic: summary
